spinmobile/__init__.py
spinmobile/client.py
spinmobile/credit.py
spinmobile/files.py
spinmobile/kyc.py
spinmobile/utils.py
spinmobile-0.2.0.dist-info/licenses/LICENSE
spinmobile-0.2.0.dist-info/METADATA
spinmobile-0.2.0.dist-info/WHEEL
spinmobile-0.2.0.dist-info/top_level.txt
spinmobile-0.2.0.dist-info/RECORD
