Metadata-Version: 2.4
Name: spinmobile
Version: 0.2.0
Summary: SpinMobile Python SDK
Requires-Python: >=3.12
License-File: LICENSE
Requires-Dist: aiohttp>=3.12.15
Dynamic: license-file
